[
    {
        "title": "",
        "source": "",
        "url": "",
        "recording_date": "2020--",
        "type": "article",
        "id": 57
    },
   
    {
        "title": "Successful Investing",
        "source": "The Costco Connection",
        "url": "http://www.costcoconnection.com/connection/202007/MobilePagedReplica.action?pm=1&folio=17#pg20",
        "recording_date": "2020-07-21",
        "type": "article",
        "id": 57
    },
    {
        "title": "Wearable Tech",
        "source": "The Costco Connection",
        "url": "http://www.costcoconnection.com/connection/202007/MobilePagedReplica.action?pm=1&folio=19#pg22",
        "recording_date": "2020-07-20",
        "type": "article",
        "id": 56
    },
    {
        "title": "A New Start",
        "source": "The Costco Connection",
        "url": "http://www.costcoconnection.com/connection/202007/MobilePagedReplica.action?pm=1&folio=15#pg18",
        "recording_date": "2020-07-16",
        "type": "article",
        "id": 55
    },
    {
        "title": "Stellar Casting",
        "source": "The Costco Connection",
        "url": "https://www.costcoconnection.ca/connectioncaeng/20200708/MobilePagedReplica.action?pm=1&folio=11#pg14",
        "recording_date": "2020-07-15",
        "type": "article",
        "id": 54
    },
    {
        "title": "Huawei believes it can supply 5G kit to UK despite US sanctions",
        "source": "The Guardian",
        "url": "https://www.theguardian.com/technology/2020/jul/11/huawei-believes-it-can-supply-5g-kit-to-uk-despite-us-sanctions",
        "recording_date": "2020-07-13",
        "type": "article",
        "id": 54
    },
    {
        "title": "Google software glitch sent some users' videos to strangers",
        "source": "The Guardian",
        "url": "https://www.theguardian.com/technology/2020/feb/04/google-software-glitch-sent-some-users-videos-to-strangers",
        "recording_date": "2020-02-05",
        "type": "article",
        "id": 58
    },
    {
        "title": "Twitter drops Grindr from ad network over 'GDPR breaches'",
        "source": "The Guardian",
        "url": "https://www.theguardian.com/technology/2020/jan/15/twitter-drops-grindr-from-ad-network-over-data-breaches",
        "recording_date": "2020-01-15",
        "type": "article",
        "id": 57
    },
    {
        "title": "We’re approaching the limits of computer power – we need new programmers now",
        "source": "The Guardian",
        "url": "https://www.theguardian.com/commentisfree/2020/jan/11/we-are-approaching-the-limits-of-computer-power-we-need-new-programmers-n-ow",
        "recording_date": "2020-01-14",
        "type": "article",
        "id": 56
    },
    {
        "title": "Grow for it",
        "source": "The Costco Connection",
        "url": "http://www.costcoconnection.ca/connectioncaeng/20200102/MobilePagedReplica.action?pm=1&folio=11#pg14",
        "recording_date": "2020-01-12",
        "type": "magazine",
        "id": 55
    },
    {
        "title": "Why Wi-Fi 6?",
        "source": "The Costco Connection",
        "url": "http://www.costcoconnection.com/connection/202001/MobilePagedReplica.action?pm=1&folio=27#pg30",
        "recording_date": "2020-01-05",
        "type": "magazine",
        "id": 54
    },
    {
        "title": "UK credit card debts fall for first time since 2013",
        "source": "The Guardian",
        "url": "https://www.theguardian.com/money/2020/jan/03/uk-credit-card-debts-fall-for-first-time-since-2013",
        "recording_date": "2020-01-03",
        "type": "article",
        "id": 53
    },
    
    {
        "title": "Get yourself cybersecure for 2020",
        "source": "The Guardian",
        "url": "https://www.theguardian.com/technology/2019/dec/31/get-cybersecure-for-2020-cybersecurity-passwords-smartphone",
        "recording_date": "2020-01-02",
        "type": "article",
        "id": 52
    },
    {
        "title": "Free speech row as US TV channel forces removal of tweets",
        "source": "The Guardian",
        "url": "https://www.theguardian.com/technology/2019/apr/15/free-speech-row-us-tv-channel-forces-removal-of-tweets",
        "recording_date": "2019-04-16",
        "type": "article",
        "id": 51
    },
    {
        "title": "Facebook to use AI to stop telling users to say hi to dead friends",
        "source": "The Guardian",
        "url": "https://www.theguardian.com/technology/2019/apr/09/facebook-to-use-artificial-intelligence-to-stop-telling-users-to-say-hi-to-dead-friends",
        "recording_date": "2019-04-09",
        "type": "article",
        "id": 50
    },
    {
        "title": "Tesla performs U-turn over store closures",
        "source": "The Guardian",
        "url": "https://www.theguardian.com/technology/2019/mar/11/tesla-performs-u-turn-over-store-closures",
        "recording_date": "2019-03-11",
        "type": "article",
        "id": 49
    },
    {
        "title": "New interracial couple emoji mark victory for partners of color",
        "source": "The Guardian",
        "url": "https://www.theguardian.com/technology/2019/mar/08/new-interracial-couple-emoji-tinder",
        "recording_date": "2019-03-10",
        "type": "article",
        "id": 48
    },
    {
        "title": "Huawei founder: US cannot crush technology firm",
        "source": "The Guardian",
        "url": "https://www.theguardian.com/technology/2019/feb/18/huawei-founder-defies-us-over-criminal-charges-against-firm",
        "recording_date": "2019-02-20",
        "type": "article",
        "id": 47
    },
    {
        "title": "Facebook 'youth team' to focus on Messenger Kids app for under-13s",
        "source": "The Guardian",
        "url": "https://www.theguardian.com/technology/2019/feb/08/facebook-youth-team-messenger-kids-app-lol-meme-hub",
        "recording_date": "2019-02-09",
        "type": "article",
        "id": 46
    },
    {
        "title": "EU recalls children's smartwatch over data fears",
        "source": "The Guardian",
        "url": "https://www.theguardian.com/technology/2019/feb/05/eu-recalls-childrens-smartwatch-over-data-fears",
        "recording_date": "2019-02-05",
        "type": "article",
        "id": 45
    },
    {
        "title": "Closure of Google+: everything you need to know",
        "source": "The Guardian",
        "url": "https://www.theguardian.com/technology/2019/feb/01/closure-google-plus-everything-you-need-to-know",
        "recording_date": "2019-02-04",
        "type": "article",
        "id": 44
    },
    {
        "title": "Tesla to cut more than 3,000 jobs because cars 'still too expensive'",
        "source": "The Guardian",
        "url": "https://www.theguardian.com/technology/2019/jan/18/tesla-to-cut-more-than-3000-jobs-because-cars-still-too-expensive-elon-musk",
        "recording_date": "2019-01-18",
        "type": "article",
        "id": 43
    },
    {
        "title": "Better caregiving",
        "source": "The Costco Connection",
        "url": "http://www.costcoconnection.ca/connectioncaeng/connectioncaeng?pg=32#pg32",
        "recording_date": "2019-01-17",
        "type": "magazine",
        "id": 42
    },
    {
        "title": "Enhancing workplace energy",
        "source": "The Costco Connection",
        "url": "http://www.costcoconnection.ca/connectioncaeng/connectioncaeng?pg=14#pg14",
        "recording_date": "2019-01-16",
        "type": "magazine",
        "id": 41
    },
    {
        "title": "Poland arrests Huawei worker on allegations of spying for China",
        "source": "The Guardian",
        "url": "https://www.theguardian.com/technology/2019/jan/11/huawei-employee-arrested-in-poland-over-chinese-spy-allegations",
        "recording_date": "2019-01-14",
        "type": "article",
        "id": 40
    },
    {
        "title": "The sounds of sports are music to my ears",
        "source": "The Guardian",
        "url": "https://www.theguardian.com/lifeandstyle/2018/nov/24/joy-of-small-things-sounds-of-sports-hannah-jane-parkinson",
        "recording_date": "2018-12-03",
        "type": "article",
        "id": 39
    },
    {
        "title": "Taking control of the clock - Time after time",
        "source": "The Costco Connection",
        "url": "http://www.costcoconnection.ca/connectioncaeng/20181112?pg=20#pg20",
        "recording_date": "2018-11-26",
        "type": "magazine",
        "id": 38
    },
    {
        "title": "Amazon hit with major data breach days before Black Friday",
        "source": "The Guardian",
        "url": "https://www.theguardian.com/technology/2018/nov/21/amazon-hit-with-major-data-breach-days-before-black-friday",
        "recording_date": "2018-11-25",
        "type": "article",
        "id": 37
    },
    {
        "title": "Your Money and You",
        "source": "The Costco Connection",
        "url": "http://www.costcoconnection.ca/connectioncaeng/20180910?pg=14#pg14",
        "recording_date": "2018-11-03",
        "type": "magazine",
        "id": 36
    },
    {
        "title": "Finding your work groove",
        "source": "The Costco Connection",
        "url": "",
        "recording_date": "2018-10-27",
        "type": "magazine",
        "id": 35
    },
    {
        "title": "'Tech tax' necessary to avoid dystopia, says leading economist",
        "source": "The Guardian",
        "url": "https://www.theguardian.com/technology/2018/oct/23/exclusive-tech-tax-jeffrey-sachs-ai-wealth-facebook-google-amazon",
        "recording_date": "2018-10-23",
        "type": "article",
        "id": 34
    },
    {
        "title": "Amazon creates 600 technology jobs in Manchester",
        "source": "The Guardian",
        "url": "https://www.theguardian.com/technology/2018/oct/18/amazon-creates-600-technology-jobs-in-manchester",
        "recording_date": "2018-10-21",
        "type": "article",
        "id": 33
    },
    {
        "title": "Four steps to a younger, smarter brain",
        "source": "The Guardian",
        "url": "https://www.theguardian.com/lifeandstyle/2018/oct/14/four-steps-to-better-brain-health",
        "recording_date": "2018-10-15",
        "type": "article",
        "id": 32
    },
    {
        "title": "Google to shut down Google+ after failing to disclose user data leak",
        "source": "The Guardian",
        "url": "https://www.theguardian.com/technology/2018/oct/08/google-plus-security-breach-wall-street-journal",
        "recording_date": "2018-10-13",
        "type": "article",
        "id": 31
    },
    {
        "title": "From Virgin to Tesla: why companies go cool on public ownership",
        "source": "The Guardian",
        "url": "https://www.theguardian.com/technology/2018/aug/09/from-virgin-to-tesla-why-companies-go-cool-on-public-ownership",
        "recording_date": "2018-10-11",
        "type": "article",
        "id": 30
    },
    {
        "title": "UK high court blocks mass privacy action against Google",
        "source": "The Guardian",
        "url": "https://www.theguardian.com/technology/2018/oct/08/uk-high-court-blocks-mass-privacy-action-against-google",
        "recording_date": "2018-10-08",
        "type": "article",
        "id": 29
    },
    {
        "title": "Asian shares fall as China set to reopen after Beijing eases policy",
        "source": "Investing.com",
        "url": "https://www.investing.com/news/stock-market-news/asian-shares-fall-as-china-set-to-reopen-after-beijing-eases-policy-1634936",
        "recording_date": "2018-10-07",
        "type": "article",
        "id": 28
    },
    {
        "title": "World markets rattled by US inflation concerns",
        "source": "The Guardian",
        "url": "https://www.theguardian.com/business/2018/oct/04/world-markets-rattled-by-us-inflation-concerns",
        "recording_date": "2018-10-04",
        "type": "article",
        "id": 27
    },
    {
        "title": "Apple, Google and Amazon named as most valuable brands in world",
        "source": "The Guardian",
        "url": "https://www.theguardian.com/technology/2018/oct/04/apple-google-and-amazon-named-as-most-valuable-brands-in-world",
        "recording_date": "2018-10-03",
        "type": "article",
        "id": 26
    },
    {
        "title": "Tencent's online music unit files for U.S. listing",
        "source": "Investing.com",
        "url": "https://www.investing.com/news/stock-market-news/tencents-online-music-unit-files-for-us-listing-1632123",
        "recording_date": "2018-10-02",
        "type": "article",
        "id": 25
    },
    {
        "title": "Katy Perry beats Bieber and Trump to top 100m Twitter followers",
        "source": "The Guardian",
        "url": "https://www.theguardian.com/music/2017/jun/17/katy-perry-beats-bieber-and-trump-to-top-100m-twitter-followers",
        "recording_date": "2018-09-30",
        "type": "article",
        "id": 24
    },
    {
        "title": "Facebook says nearly 50m users compromised in huge security breach",
        "source": "The Guardian",
        "url": "https://www.theguardian.com/technology/2018/sep/28/facebook-50-million-user-accounts-security-berach",
        "recording_date": "2018-09-29",
        "type": "article",
        "id": 23
    },
    {
        "title": "SEC sues Elon Musk for fraud and seeks to bar him from leading a company",
        "source": "The Guardian",
        "url": "https://www.theguardian.com/technology/2018/sep/27/sec-sues-elon-musk-and-tesla-over-plans-to-make-company-private",
        "recording_date": "2018-09-28",
        "type": "article",
        "id": 22
    },
    {
        "title": "Instagram co-founders resign to explore 'creativity again'",
        "source": "The Guardian",
        "url": "https://www.theguardian.com/technology/2018/sep/25/instagram-co-founders-resign-to-explore-creativity-again",
        "recording_date": "2018-09-25",
        "type": "article",
        "id": 21
    },
    {
        "title": "Speech recognition is tech's next giant leap, says Google",
        "source": "The Guardian",
        "url": "https://www.theguardian.com/technology/2018/sep/24/speech-recognition-tech-google",
        "recording_date": "2018-09-24",
        "type": "article",
        "id": 20
    },
    {
        "title": "Amazon becomes world's second company to be valued at $1tn",
        "source": "The Guardian",
        "url": "https://www.theguardian.com/technology/2018/sep/04/amazon-becomes-worlds-second-1tn-company",
        "recording_date": "2018-09-05",
        "type": "article",
        "id": 19
    },
    {
        "title": "Tips to Improve your writing for business",
        "source": "The Costco Connection",
        "url": "",
        "recording_date": "2018-07-02",
        "type": "magazine",
        "id": 18
    },
    {
        "title": "Managing a project through small steps",
        "source": "The Costco Connection",
        "url": "",
        "recording_date": "2018-07-01",
        "type": "magazine",
        "id": 17
    },
    {
        "title": "Lite fantastic- why slimmed down phone apps are the fast way forward",
        "source": "The Guardian",
        "url": "https://www.theguardian.com/technology/2018/jun/29/lite-fantastic-why-slimmed-down-phone-apps-are-the-fast-way-forward",
        "recording_date": "2018-06-30",
        "type": "article",
        "id": 16
    },
    {
        "title": "Our guide to the death of the telephone - Part 1",
        "source": "The Guardian",
        "url": "https://www.theguardian.com/global/2018/jun/24/landline-mobile-guide-death-telephone",
        "recording_date": "2018-06-25",
        "type": "article",
        "id": 15
    },
    {
        "title": "What Goes around; Free Exchange",
        "source": "The Economist",
        "url": "https://www.highbeam.com/doc/1G1-542667309.html",
        "recording_date": "2018-06-24",
        "type": "article",
        "id": 14
    },
    {
        "title": "Computer algorithms can test the dodginess of published results",
        "source": "The Economist",
        "url": "https://www.economist.com/science-and-technology/2018/06/16/computer-algorithms-can-test-the-dodginess-of-published-results",
        "recording_date": "2018-06-23",
        "type": "article",
        "id": 13
    },
    {
        "title": "The engineering sector needs more women",
        "source": "The Guardian",
        "url": "https://www.theguardian.com/technology/2018/jun/22/the-engineering-sector-needs-more-women",
        "recording_date": "2018-06-22",
        "type": "article",
        "id": 12
    },
    {
        "title": "Netflix chief of communications leaving after reports of using N-word",
        "source": "The Guardian",
        "url": "https://www.theguardian.com/media/2018/jun/22/netflix-chief-of-communications-leaving-after-reports-of-using-n-word",
        "recording_date": "2018-06-21",
        "type": "article",
        "id": 11
    },
    {
        "title": "Some American firms will be hit hard by retaliatory tariffs",
        "source": "The Economist",
        "url": "https://www.economist.com/finance-and-economics/2018/06/07/american-firms-will-be-hit-hard-by-retaliatory-tariffs",
        "recording_date": "2018-06-17",
        "type": "article",
        "id": 10
    },
    {
        "title": "Google runs into more flak on artificial intelligence",
        "source": "The Economist",
        "url": "https://www.economist.com/business/2018/06/14/google-runs-into-more-flak-on-artificial-intelligence",
        "recording_date": "2018-06-16",
        "type": "article",
        "id": 9
    },
    {
        "title": "High Performance Habits - Summary Guide",
        "source": "Brendon Burchard",
        "url": "https://www.amazon.ca/High-Performance-Habits-Extraordinary-People/dp/1401952852",
        "recording_date": "2018-06-15",
        "type": "book",
        "id": 8
    },
    {
        "title": "Facebook advertises for 'fake news' fact checkers",
        "source": "The Guardian",
        "url": "https://www.theguardian.com/technology/2018/jun/08/facebook-advertises-for-fake-news-fact-checkers",
        "recording_date": "2018-06-10",
        "type": "article",
        "id": 7
    },
    {
        "title": "Apple inches closer to $1tn mark as Wall Street tech panic dissipates",
        "source": "The Guardian",
        "url": "https://www.theguardian.com/technology/2018/jun/09/apple-first-company-valued-at-1-trillion",
        "recording_date": "2018-06-09",
        "type": "article",
        "id": 6
    },
    {
        "title": "How can I stop an unexpected Windows 10 update?",
        "source": "The Guardian",
        "url": "https://www.theguardian.com/technology/askjack/2018/may/17/how-can-i-stop-an-unexpected-windows-10-update",
        "recording_date": "2018-06-08",
        "type": "article",
        "id": 5
    },
    {
        "title": "Scooters littering US city streets shout at people: 'Unlock me or I'll call the police'",
        "source": "The Guardian",
        "url": "https://www.theguardian.com/technology/2018/jun/07/scooters-littering-city-streets-shout-at-people-unlock-me-or-ill-call-the-police",
        "recording_date": "2018-06-07",
        "type": "article",
        "id": 4
    },
    {
        "title": "iOS 12: everything you need to know about new iPhone features",
        "source": "The Guardian",
        "url": "https://www.theguardian.com/technology/2018/jun/05/ios-12-iphone-new-operating-system-everything-you-need-to-know-notifications-privacy-emoji",
        "recording_date": "2018-06-05",
        "type": "article",
        "id": 3
    },
    {
        "title": "Microsoft is buying code-sharing site GitHub for $7.5bn",
        "source": "The Guardian",
        "url": "https://www.theguardian.com/technology/2018/jun/04/microsoft-is-buying-code-sharing-site-github-say-reports",
        "recording_date": "2018-06-04",
        "type": "article",
        "id": 2
    },
    {
        "title": "Teens are abandoning Facebook in dramatic numbers",
        "source": "The Guardian",
        "url": "https://www.theguardian.com/technology/2018/jun/01/facebook-teens-leaving-instagram-snapchat-study-user-numbers",
        "recording_date": "2018-06-03",
        "type": "article",
        "id": 1
    }
]